open_dread_rando/__init__.py
open_dread_rando/__main__.py
open_dread_rando/cli.py
open_dread_rando/constants.py
open_dread_rando/dread_patcher.py
open_dread_rando/logger.py
open_dread_rando/output_config.py
open_dread_rando/patch_util.py
open_dread_rando/patcher_editor.py
open_dread_rando/validator_with_default.py
open_dread_rando/version.py
open_dread_rando/__pyinstaller/__init__.py
open_dread_rando/__pyinstaller/hook-open_dread_rando.py
open_dread_rando/cosmetic_patches/__init__.py
open_dread_rando/cosmetic_patches/missile_color_patcher.py
open_dread_rando/door_locks/__init__.py
open_dread_rando/door_locks/custom_door_types.py
open_dread_rando/door_locks/door_patcher.py
open_dread_rando/files/__init__.py
open_dread_rando/files/custom_scenario.lua
open_dread_rando/files/msemenu_mainmenu.lua
open_dread_rando/files/randomizer_powerup.lua
open_dread_rando/files/schema.json
open_dread_rando/files/exefs_patches/.gitignore
open_dread_rando/files/exefs_patches/49161D9CCBC15DF944D0B6278A3C446C006B0BE8.ips
open_dread_rando/files/exefs_patches/646761F643AFEBB379EDD5E6A5151AF2CEF93DC1.ips
open_dread_rando/files/levels/readme.txt
open_dread_rando/files/levels/s010_cave.lc.lua
open_dread_rando/files/levels/s020_magma.lc.lua
open_dread_rando/files/levels/s030_baselab.lc.lua
open_dread_rando/files/levels/s040_aqua.lc.lua
open_dread_rando/files/levels/s050_forest.lc.lua
open_dread_rando/files/levels/s060_quarantine.lc.lua
open_dread_rando/files/levels/s070_basesanc.lc.lua
open_dread_rando/files/levels/s080_shipyard.lc.lua
open_dread_rando/files/levels/s090_skybase.lc.lua
open_dread_rando/files/lua_libraries/bit.lua
open_dread_rando/files/lua_libraries/data_structures.lua
open_dread_rando/files/lua_libraries/death_counter.lua
open_dread_rando/files/lua_libraries/disconnect_gui.lua
open_dread_rando/files/lua_libraries/guilib.lua
open_dread_rando/files/lua_libraries/input_handling.lua
open_dread_rando/files/lua_libraries/room_names.lua
open_dread_rando-2.17.0.dist-info/licenses/LICENSE
open_dread_rando-2.17.0.dist-info/METADATA
open_dread_rando-2.17.0.dist-info/WHEEL
open_dread_rando-2.17.0.dist-info/entry_points.txt
open_dread_rando-2.17.0.dist-info/top_level.txt
open_dread_rando-2.17.0.dist-info/RECORD
