Metadata-Version: 2.4
Name: open-dread-rando
Version: 2.17.0
Summary: An open source randomizer patcher for Metroid Dread.
Project-URL: Homepage, https://github.com/randovania/open-dread-rando
Classifier: License :: OSI Approved :: GNU General Public License v3 (GPLv3)
Classifier: Development Status :: 3 - Alpha
Classifier: Intended Audience :: Developers
Classifier: Programming Language :: Python :: 3.9
Requires-Python: >=3.10
License-File: LICENSE
Requires-Dist: mercury-engine-data-structures>=0.33
Requires-Dist: jsonschema>=4.0.0
Requires-Dist: json-delta>=2.0.2
Requires-Dist: open-dread-rando-exlaunch>=1.1.0
Provides-Extra: test
Requires-Dist: lupa; extra == "test"
Requires-Dist: pytest; extra == "test"
Requires-Dist: pytest-cov; extra == "test"
Requires-Dist: pytest-mock; extra == "test"
Dynamic: license-file
